updogfx/__init__.py
updogfx/main.py
updogfx-0.2.7.dist-info/METADATA
updogfx-0.2.7.dist-info/WHEEL
updogfx-0.2.7.dist-info/entry_points.txt
updogfx-0.2.7.dist-info/top_level.txt
updogfx-0.2.7.dist-info/RECORD
