Metadata-Version: 2.4
Name: updogfx
Version: 0.2.7
Summary: A simple file server with Cloudflare tunneling
Author: EFXTv
